sc_corporate_analysis/__init__.py
sc_corporate_analysis/main.py
sc_corporate_analysis/analyzer/__init__.py
sc_corporate_analysis/analyzer/base_analyzer.py
sc_corporate_analysis/analyzer/common_manager_deposit_analyzer.py
sc_corporate_analysis/analyzer/manager_deposit_analyzer.py
sc_corporate_analysis/summary/__init__.py
sc_corporate_analysis/summary/branch_summary_analyzer.py
sc_corporate_analysis/tests/__init__.py
sc_corporate_analysis/tests/sample_config/production.yml
sc_corporate_analysis/utils/__init__.py
sc_corporate_analysis/utils/manifest_utils.py
sc_corporate_analysis-0.0.4.dist-info/LICENSE
sc_corporate_analysis-0.0.4.dist-info/METADATA
sc_corporate_analysis-0.0.4.dist-info/WHEEL
sc_corporate_analysis-0.0.4.dist-info/entry_points.txt
sc_corporate_analysis-0.0.4.dist-info/top_level.txt
sc_corporate_analysis-0.0.4.dist-info/RECORD
